LICENSE.txt
MANIFEST.in
README.rst
setup.cfg
setup.py
bin/ktbs
bin/ktbs-add-stats
bin/ktbs-infos
bin/ktbs-rebase
bin/ktbs-reset-locks
bin/simple-collector
lib/kTBS.egg-info/PKG-INFO
lib/kTBS.egg-info/SOURCES.txt
lib/kTBS.egg-info/dependency_links.txt
lib/kTBS.egg-info/requires.txt
lib/kTBS.egg-info/top_level.txt
lib/ktbs/__init__.py
lib/ktbs/client.py
lib/ktbs/config.py
lib/ktbs/namespace.py
lib/ktbs/standalone.py
lib/ktbs/time.py
lib/ktbs/utils.py
lib/ktbs/api/__init__.py
lib/ktbs/api/base.py
lib/ktbs/api/builtin_method.py
lib/ktbs/api/ktbs_root.py
lib/ktbs/api/method.py
lib/ktbs/api/obsel.py
lib/ktbs/api/resource.py
lib/ktbs/api/trace.py
lib/ktbs/api/trace_model.py
lib/ktbs/api/trace_obsels.py
lib/ktbs/api/trace_stats.py
lib/ktbs/engine/__init__.py
lib/ktbs/engine/base.py
lib/ktbs/engine/builtin_method.py
lib/ktbs/engine/data_graph.py
lib/ktbs/engine/ktbs_root.py
lib/ktbs/engine/lock.py
lib/ktbs/engine/method.py
lib/ktbs/engine/obsel.py
lib/ktbs/engine/resource.py
lib/ktbs/engine/service.py
lib/ktbs/engine/trace.py
lib/ktbs/engine/trace_model.py
lib/ktbs/engine/trace_obsels.py
lib/ktbs/engine/trace_stats.py
lib/ktbs/methods/__init__.py
lib/ktbs/methods/abstract.py
lib/ktbs/methods/filter.py
lib/ktbs/methods/fsa.py
lib/ktbs/methods/fusion.py
lib/ktbs/methods/hrules.py
lib/ktbs/methods/interface.py
lib/ktbs/methods/isparql.py
lib/ktbs/methods/parallel.py
lib/ktbs/methods/pipe.py
lib/ktbs/methods/sparql.py
lib/ktbs/methods/utils.py
lib/ktbs/plugins/__init__.py
lib/ktbs/plugins/activitystreams.py
lib/ktbs/plugins/auth2subject.py
lib/ktbs/plugins/authx.py
lib/ktbs/plugins/cors.py
lib/ktbs/plugins/hydra.py
lib/ktbs/plugins/inspector.py
lib/ktbs/plugins/meth_external.py
lib/ktbs/plugins/meth_feed.py
lib/ktbs/plugins/meth_seq.py
lib/ktbs/plugins/meth_xapi.py
lib/ktbs/plugins/post_via_get.py
lib/ktbs/plugins/profiler.py
lib/ktbs/plugins/simple_model.py
lib/ktbs/plugins/sparql_endpoints.py
lib/ktbs/plugins/stats_per_type.py
lib/ktbs/plugins/stats_subjects.py
lib/ktbs/plugins/taaabs_ui.py
lib/ktbs/plugins/virtuoso_sparql.py
lib/ktbs/plugins/xgereco_obsel_table.py
lib/ktbs/serpar/__init__.py
lib/ktbs/serpar/csv_serializers.py
