Metadata-Version: 1.0
Name: kTBS
Version: 0.6
Summary: A kernel for trace-based systems
Home-page: http://github.com/ktbs/ktbs
Author: Pierre-Antoine Champin, Françoise Conil
Author-email: sbt-dev@liris.cnrs.fr
License: LGPL v3
Platform: OS Independant
